{
  "name": "Poisoning",
  "questions": [
    {
      "questionText": "The antidote for opioid overdose with respiratory depression is:",
      "optionA": "Atropine",
      "optionB": "Naloxone",
      "optionC": "N-acetylcysteine",
      "optionD": "Flumazenil",
      "correctAnswer": "B",
      "explanation": "Naloxone is a competitive opioid receptor antagonist reversing respiratory depression.",
      "difficulty": "EASY",
      "source": "Harrison",
      "previousYear": true,
      "conceptTag": "Opioid Toxicity",
      "tags": "Medicine,Poisoning,PYQ,Emergency"
    },
    {
      "questionText": "The antidote for acetaminophen toxicity is:",
      "optionA": "Pralidoxime",
      "optionB": "N-acetylcysteine",
      "optionC": "Naloxone",
      "optionD": "Methylene blue",
      "correctAnswer": "B",
      "explanation": "N-acetylcysteine replenishes glutathione and reduces hepatic injury in acetaminophen poisoning.",
      "difficulty": "EASY",
      "source": "Harrison",
      "previousYear": true,
      "conceptTag": "Drug Overdose",
      "tags": "Medicine,Poisoning,PYQ"
    },
    {
      "questionText": "A cholinergic toxidrome with salivation, lacrimation, urination, diarrhea, and miosis suggests poisoning by:",
      "optionA": "Organophosphates",
      "optionB": "Opioids",
      "optionC": "Methanol",
      "optionD": "Lead",
      "correctAnswer": "A",
      "explanation": "Organophosphate exposure causes acetylcholinesterase inhibition and cholinergic excess.",
      "difficulty": "EASY",
      "source": "Harrison",
      "previousYear": true,
      "conceptTag": "Cholinergic Syndrome",
      "tags": "Medicine,Poisoning,PYQ"
    },
    {
      "questionText": "Initial antidotal therapy in organophosphate poisoning includes:",
      "optionA": "Atropine and pralidoxime",
      "optionB": "Naloxone and glucose",
      "optionC": "N-acetylcysteine alone",
      "optionD": "Only diazepam",
      "correctAnswer": "A",
      "explanation": "Atropine counters muscarinic effects and pralidoxime reactivates acetylcholinesterase when given early.",
      "difficulty": "MEDIUM",
      "source": "Harrison",
      "previousYear": true,
      "conceptTag": "Antidotes",
      "tags": "Medicine,Poisoning,PYQ,Emergency"
    },
    {
      "questionText": "A high anion gap metabolic acidosis with visual symptoms is classically seen in:",
      "optionA": "Methanol poisoning",
      "optionB": "Carbon monoxide poisoning",
      "optionC": "Paracetamol toxicity",
      "optionD": "Iron poisoning",
      "correctAnswer": "A",
      "explanation": "Methanol metabolizes to formic acid causing severe acidosis and optic toxicity.",
      "difficulty": "MEDIUM",
      "source": "Harrison",
      "previousYear": true,
      "conceptTag": "Toxic Alcohols",
      "tags": "Medicine,Poisoning,PYQ"
    },
    {
      "questionText": "Preferred antidotal therapy for methanol poisoning includes:",
      "optionA": "Fomepizole or ethanol",
      "optionB": "Naloxone",
      "optionC": "Pralidoxime",
      "optionD": "Atropine",
      "correctAnswer": "A",
      "explanation": "Fomepizole inhibits alcohol dehydrogenase and prevents toxic metabolite formation.",
      "difficulty": "MEDIUM",
      "source": "Harrison",
      "previousYear": true,
      "conceptTag": "Toxicology Management",
      "tags": "Medicine,Poisoning,PYQ"
    },
    {
      "questionText": "A patient exposed to smoke inhalation with headache and cherry-red skin should be suspected to have:",
      "optionA": "Cyanide poisoning only",
      "optionB": "Carbon monoxide poisoning",
      "optionC": "Lead poisoning",
      "optionD": "Mercury poisoning",
      "correctAnswer": "B",
      "explanation": "CO poisoning causes tissue hypoxia from carboxyhemoglobin formation; pulse oximetry may be misleading.",
      "difficulty": "EASY",
      "source": "Harrison",
      "previousYear": true,
      "conceptTag": "Gas Poisoning",
      "tags": "Medicine,Poisoning,PYQ"
    },
    {
      "questionText": "The definitive treatment in severe carbon monoxide poisoning is:",
      "optionA": "Only room air",
      "optionB": "100 percent oxygen and consider hyperbaric oxygen in severe cases",
      "optionC": "N-acetylcysteine",
      "optionD": "Pralidoxime",
      "correctAnswer": "B",
      "explanation": "High-flow oxygen reduces carboxyhemoglobin half-life; hyperbaric oxygen is used for selected severe cases.",
      "difficulty": "MEDIUM",
      "source": "Harrison",
      "previousYear": true,
      "conceptTag": "CO Management",
      "tags": "Medicine,Poisoning,PYQ,Critical Care"
    },
    {
      "questionText": "The classic acid-base disorder in salicylate toxicity is:",
      "optionA": "Pure respiratory acidosis",
      "optionB": "Mixed respiratory alkalosis and metabolic acidosis",
      "optionC": "Pure metabolic alkalosis",
      "optionD": "Normal acid-base status always",
      "correctAnswer": "B",
      "explanation": "Salicylate poisoning causes early respiratory alkalosis with later high anion gap metabolic acidosis.",
      "difficulty": "HARD",
      "source": "Harrison",
      "previousYear": true,
      "conceptTag": "Salicylate Poisoning",
      "tags": "Medicine,Poisoning,PYQ"
    },
    {
      "questionText": "A key urinary alkalinization indication in toxicology is:",
      "optionA": "Opioid overdose",
      "optionB": "Salicylate poisoning",
      "optionC": "Benzodiazepine overdose",
      "optionD": "Organophosphate poisoning",
      "correctAnswer": "B",
      "explanation": "Urinary alkalinization enhances renal salicylate excretion in appropriate patients.",
      "difficulty": "MEDIUM",
      "source": "Harrison",
      "previousYear": true,
      "conceptTag": "Enhanced Elimination",
      "tags": "Medicine,Poisoning,PYQ"
    },
    {
      "questionText": "The antidote for methemoglobinemia in symptomatic patients is:",
      "optionA": "Methylene blue",
      "optionB": "Naloxone",
      "optionC": "Atropine",
      "optionD": "Flumazenil",
      "correctAnswer": "A",
      "explanation": "Methylene blue reduces methemoglobin back to hemoglobin in most cases.",
      "difficulty": "MEDIUM",
      "source": "Harrison",
      "previousYear": false,
      "conceptTag": "Oxidant Injury",
      "tags": "Medicine,Poisoning"
    },
    {
      "questionText": "In unknown poisoning with reduced consciousness, the immediate priority in emergency management is:",
      "optionA": "Wait for toxicology report",
      "optionB": "Airway, breathing, circulation stabilization",
      "optionC": "Induce emesis routinely",
      "optionD": "Start broad-spectrum antibiotics",
      "correctAnswer": "B",
      "explanation": "Initial toxicology management always prioritizes airway, breathing, and circulation.",
      "difficulty": "EASY",
      "source": "Harrison",
      "previousYear": true,
      "conceptTag": "Poisoning Approach",
      "tags": "Medicine,Poisoning,PYQ,Emergency"
    }
  ]
}